dnsupdater/__init__.py
dnsupdater/cloudflare.py
dnsupdater/dnsupdater.py
dnsupdater/ip.py
dnsupdater/route53.py
dnsupdater-0.1.0.dist-info/METADATA
dnsupdater-0.1.0.dist-info/WHEEL
dnsupdater-0.1.0.dist-info/entry_points.txt
dnsupdater-0.1.0.dist-info/licenses/LICENSE
dnsupdater-0.1.0.dist-info/RECORD
