Metadata-Version: 2.4
Name: dnsupdater
Version: 0.1.0
Summary: Update an Amazon Route53 or Cloudflare record with your current public IP address.
Project-URL: Homepage, https://github.com/diegofd/dnsupdater
Project-URL: Issues, https://github.com/diegofd/dnsupdater/issues
Author-email: Diego Fernandez Duran <diego@goedi.net>
License-File: LICENSE
Classifier: License :: OSI Approved :: MIT License
Classifier: Operating System :: OS Independent
Classifier: Programming Language :: Python :: 3
Requires-Python: >=3.8
